LICENSE
MANIFEST.in
README.md
requirements.txt
setup.cfg
setup.py
dockerfiles/standalone-chrome-ffmpeg/entry_point.sh
dockerfiles/standalone-chrome-ffmpeg/ffserver.conf-orig
dockerfiles/standalone-firefox-ffmpeg/entry_point.sh
dockerfiles/standalone-firefox-ffmpeg/ffserver.conf-orig
selenium_docker/__init__.py
selenium_docker/base.py
selenium_docker/errors.py
selenium_docker/helpers.py
selenium_docker/meta.py
selenium_docker/pool.py
selenium_docker/proxy.py
selenium_docker/utils.py
selenium_docker.egg-info/PKG-INFO
selenium_docker.egg-info/SOURCES.txt
selenium_docker.egg-info/dependency_links.txt
selenium_docker.egg-info/requires.txt
selenium_docker.egg-info/top_level.txt
selenium_docker/drivers/__init__.py
selenium_docker/drivers/chrome.py
selenium_docker/drivers/firefox.py
tests/conftest.py
tests/test_drivers.py
tests/test_factory.py
tests/test_pool.py
tests/test_proxy.py
tests/test_utils.py
tests/__pycache__/conftest.cpython-27-PYTEST.pyc
tests/__pycache__/conftest.cpython-36-PYTEST.pyc
tests/__pycache__/test_drivers.cpython-27-PYTEST.pyc
tests/__pycache__/test_drivers.cpython-36-PYTEST.pyc
tests/__pycache__/test_factory.cpython-27-PYTEST.pyc
tests/__pycache__/test_factory.cpython-36-PYTEST.pyc
tests/__pycache__/test_pool.cpython-27-PYTEST.pyc
tests/__pycache__/test_pool.cpython-36-PYTEST.pyc
tests/__pycache__/test_proxy.cpython-27-PYTEST.pyc
tests/__pycache__/test_proxy.cpython-36-PYTEST.pyc
tests/__pycache__/test_utils.cpython-27-PYTEST.pyc
tests/__pycache__/test_utils.cpython-36-PYTEST.pyc