Metadata-Version: 1.1
Name: selenium-docker
Version: 0.5.0
Summary: Additional selenium drivers that utilize docker containers for their UI.
Home-page: https://github.com/vivint/selenium-council
Author: Blake VandeMerwe
Author-email: blake.vandemerwe@vivint.com
License: UNKNOWN
Platform: any
Classifier: Topic :: Software Development :: Libraries
Classifier: Natural Language :: English
Classifier: License :: OSI Approved :: Apache Software License
Classifier: Intended Audience :: Developers
Classifier: Development Status :: 4 - Beta
Classifier: Programming Language :: Python
Classifier: Programming Language :: Python :: 2.7
Classifier: Programming Language :: Python :: 3.5
Classifier: Programming Language :: Python :: 3.6
